apjson/__init__.py
apjson/pretty.py
apjson/utils.py
apjson-0.0.3.dist-info/LICENSE
apjson-0.0.3.dist-info/METADATA
apjson-0.0.3.dist-info/WHEEL
apjson-0.0.3.dist-info/top_level.txt
apjson-0.0.3.dist-info/RECORD
