Metadata-Version: 2.1
Name: apjson
Version: 0.0.3
Summary: A simple asynchronus json prettifier.
Home-page: UNKNOWN
Author: nect
License: MIT License
Keywords: prettifier json async decorator light
Platform: UNKNOWN
Classifier: Development Status :: 3 - Alpha
Classifier: License :: OSI Approved :: MIT License
Classifier: Programming Language :: Python :: 3
Classifier: Operating System :: OS Independent
Classifier: Topic :: Software Development :: Libraries
Classifier: Natural Language :: English
Classifier: Intended Audience :: Developers
Requires-Python: >=3.5, <4
Provides-Extra: dev
Requires-Dist: check-manifest ; extra == 'dev'
